shattered/__init__.py
shattered/cli.py
shattered/shattered.py
shattered-0.5.0.dist-info/entry_points.txt
shattered-0.5.0.dist-info/WHEEL
shattered-0.5.0.dist-info/METADATA
shattered-0.5.0.dist-info/RECORD
