Metadata-Version: 2.1
Name: shattered
Version: 0.5.0
Summary: STOMP meets bottle.py
Home-page: https://github.com/bradshjg/shattered
License: MIT
Author: Jimmy Bradshaw
Author-email: james.g.bradshaw@gmail.com
Requires-Python: >=3.6,<4.0
Classifier: License :: OSI Approved :: MIT License
Classifier: Programming Language :: Python :: 3
Classifier: Programming Language :: Python :: 3.6
Classifier: Programming Language :: Python :: 3.7
Classifier: Programming Language :: Python :: 3.8
Classifier: Programming Language :: Python :: 3.9
Requires-Dist: stomp.py (>=6.0.0,<7.0.0)
Project-URL: Repository, https://github.com/bradshjg/shattered
